SimplestSimulatedAnnleaning/__init__.py
SimplestSimulatedAnnleaning/cooling.py
SimplestSimulatedAnnleaning/mut_examples.py
SimplestSimulatedAnnleaning/simulated_annealing.py
SimplestSimulatedAnnealing-1.0.2.dist-info/LICENSE
SimplestSimulatedAnnealing-1.0.2.dist-info/METADATA
SimplestSimulatedAnnealing-1.0.2.dist-info/WHEEL
SimplestSimulatedAnnealing-1.0.2.dist-info/top_level.txt
SimplestSimulatedAnnealing-1.0.2.dist-info/RECORD
