Metadata-Version: 2.1
Name: SimplestSimulatedAnnealing
Version: 1.0.2
Summary: Flexible implementation of Simulated Annealing algorithm for function minimization
Home-page: https://github.com/PasaOpasen/SimplestSimulatedAnnealing
Author: Demetry Pascal
Author-email: qtckpuhdsa@gmail.com
Maintainer: ['Demetry Pascal']
License: UNKNOWN
Keywords: solve,optimization,problem,fast,combinatorial,easy,evolution,continual,simulated-annealing
Platform: UNKNOWN
Classifier: Programming Language :: Python :: 3
Classifier: License :: OSI Approved :: MIT License
Classifier: Operating System :: OS Independent
Classifier: Topic :: Software Development :: Libraries :: Python Modules
Requires-Dist: numpy
Requires-Dist: matplotlib
